MyResources/__init__.py
MyResources/__version__.py
MyResources/core.py
MyResources-5.3.0.dist-info/METADATA
MyResources-5.3.0.dist-info/RECORD
MyResources-5.3.0.dist-info/WHEEL
MyResources-5.3.0.dist-info/top_level.txt
