Metadata-Version: 2.1
Name: MyResources
Version: 5.3.0
Summary: Simple utilities to assist with deep learning text classification.
Home-page: https://github.com/JPatrick9793/test_project.git
Author: John Conway
Author-email: john.conway@novaiq.io
License: MIT
Platform: UNKNOWN
Classifier: License :: OSI Approved :: MIT License
Classifier: Programming Language :: Python
Classifier: Programming Language :: Python :: 3
Classifier: Programming Language :: Python :: 3.6
Classifier: Programming Language :: Python :: Implementation :: CPython
Classifier: Programming Language :: Python :: Implementation :: PyPy
Requires-Python: >=3.6.0
